Metadata-Version: 2.1
Name: quantumlib
Version: 0.0.106
Summary: Quantum calculations
Home-page: https://github.com/alttch/quantumlib
Author: Altertech
Author-email: div@altertech.com
License: MIT
Platform: UNKNOWN
Classifier: Programming Language :: Python :: 3
Classifier: License :: OSI Approved :: MIT License
Classifier: Topic :: Software Development :: Libraries
